kaiju_jsonrpc/__init__.py
kaiju_jsonrpc/parser.py
kaiju_jsonrpc/py.typed
kaiju_jsonrpc/router.py
kaiju_jsonrpc-0.1.1.dist-info/METADATA
kaiju_jsonrpc-0.1.1.dist-info/WHEEL
kaiju_jsonrpc-0.1.1.dist-info/top_level.txt
kaiju_jsonrpc-0.1.1.dist-info/RECORD
